strategy/__init__.py
strategy/account.py
strategy/backtest.py
strategy/candle.py
strategy/chainable.py
strategy/common.py
strategy/currency.py
strategy/exchange.py
strategy/framework.py
strategy/futures.py
strategy/index.py
strategy/indicator.py
strategy/market_data.py
strategy/okex.py
strategy/okex_for_spot.py
strategy/okex_trade.py
strategy/orderbook.py
strategy/singleton.py
strategy/technical_analysis.py
strategy/ticker.py
strategy/trade.py
strategy/trade_tool.py
strategy/tradetest.py
strategy/utf8logger.py
strategy/volume.py
mathlab_strategy_andrete-0.0.4.dist-info/LICENSE
mathlab_strategy_andrete-0.0.4.dist-info/METADATA
mathlab_strategy_andrete-0.0.4.dist-info/WHEEL
mathlab_strategy_andrete-0.0.4.dist-info/top_level.txt
mathlab_strategy_andrete-0.0.4.dist-info/RECORD
